OverwatchAchievementExporter/__init__.py
OverwatchAchievementExporter/achievements.py
OverwatchAchievementExporter/exporter.py
OverwatchAchievementExporter-1.0.1.dist-info/LICENSE.txt
OverwatchAchievementExporter-1.0.1.dist-info/METADATA
OverwatchAchievementExporter-1.0.1.dist-info/WHEEL
OverwatchAchievementExporter-1.0.1.dist-info/top_level.txt
OverwatchAchievementExporter-1.0.1.dist-info/RECORD
